image_generator_alkosenko/__init__.py
image_generator_alkosenko/image_generator.py
image_generator_alkosenko-0.0.1.dist-info/METADATA
image_generator_alkosenko-0.0.1.dist-info/WHEEL
image_generator_alkosenko-0.0.1.dist-info/licenses/LICENSE
image_generator_alkosenko-0.0.1.dist-info/RECORD
