Metadata-Version: 2.1
Name: image_generator_alkosenko
Version: 0.0.1
Summary: Image generator
Author-email: Alexey Kosenko <box@alkosenko.tech>
License-File: LICENSE
Classifier: License :: OSI Approved :: MIT License
Classifier: Operating System :: OS Independent
Classifier: Programming Language :: Python :: 3
Requires-Python: >=3.9
